{
  "status": "ok",
  "media": {
    "count": 16073,
    "page_info": {
      "has_previous_page": true,
      "start_cursor": "AQApIaGIkdD7-P76ZKTpVJ8anAJIgJExmgHgHGB5E5N7BCOP_MCyjZ-F_Wi8jrausk9rjomd9SUukzcaZbwwUSWmzxHcYHpWEJz3kTgRm72VfoqubX2TDHURdmGz33WqcCk",
      "end_cursor": "AQCzlJvu2MLbs2lv0KxUlgtfe4FCP9wZhhuTAb3_z3ZIpiuEAALVslg3jbQdvu44VgKCiIjIISS86dorlkxghAUXgTv4s3plY9m-AC_l5UQa7zhiXW5JKXVVIapozSbn6fQ",
      "has_next_page": true
    },
    "nodes": [
      {
        "code": "zfK9QMmh_D",
        "date": 1424787619,
        "dimensions": {
          "width": 640,
          "height": 640
        },
        "comments": {
          "count": 13
        },
        "caption": "Minguante\n#oca#niemeyer#niemeyerworks#oscarniemeyer#arquitetura #architecture #reflexo#minguante#espelho#pinacotecasp #dicas_sp #coolsampa #realcoolsampa #InstaSize#reflexion#mirror#moonlight#luaminguante",
        "likes": {
          "count": 55
        },
        "owner": {
          "id": "525256670"
        },
        "thumbnail_src": "https://igcdn-photos-g-a.akamaihd.net/hphotos-ak-xtf1/t51.2885-15/e15/10986013_612541568891694_455340992_n.jpg?ig_cache_key=OTI3NTA4MjM4MDA2MDk5OTA3.2",
        "is_video": false,
        "id": "927508238006099907",
        "display_src": "https://igcdn-photos-g-a.akamaihd.net/hphotos-ak-xtf1/t51.2885-15/e15/10986013_612541568891694_455340992_n.jpg?ig_cache_key=OTI3NTA4MjM4MDA2MDk5OTA3.2"
      },
      {
        "code": "BEB2rPhSvav",
        "date": 1460311129,
        "dimensions": {
          "width": 1080,
          "height": 1080
        },
        "comments": {
          "count": 0
        },
        "caption": "#brazil #saopaulo #ibirapuera #sparte #arquitetura #niemeyer #visaourbanaiz",
        "likes": {
          "count": 10
        },
        "owner": {
          "id": "1697564796"
        },
        "thumbnail_src": "https://igcdn-photos-g-a.akamaihd.net/hphotos-ak-xfp1/t51.2885-15/s640x640/sh0.08/e35/12530916_1087056814666230_941617418_n.jpg?ig_cache_key=MTIyNTUwMTAzOTczNTI3MzEzNQ%3D%3D.2",
        "is_video": false,
        "id": "1225501039735273135",
        "display_src": "https://igcdn-photos-g-a.akamaihd.net/hphotos-ak-xfp1/t51.2885-15/e35/12530916_1087056814666230_941617418_n.jpg?ig_cache_key=MTIyNTUwMTAzOTczNTI3MzEzNQ%3D%3D.2"
      },
      {
        "code": "BEG5lv2SvZe",
        "date": 1460480429,
        "dimensions": {
          "width": 1080,
          "height": 1080
        },
        "comments": {
          "count": 0
        },
        "caption": "#visaourbanaiz",
        "likes": {
          "count": 5
        },
        "owner": {
          "id": "1697564796"
        },
        "thumbnail_src": "https://igcdn-photos-a-a.akamaihd.net/hphotos-ak-xaf1/t51.2885-15/s640x640/sh0.08/e35/12912403_464889710371112_1903786350_n.jpg?ig_cache_key=MTIyNjkyMTIzMTE1MzU1OTEzNA%3D%3D.2",
        "is_video": false,
        "id": "1226921231153559134",
        "display_src": "https://igcdn-photos-a-a.akamaihd.net/hphotos-ak-xaf1/t51.2885-15/e35/12912403_464889710371112_1903786350_n.jpg?ig_cache_key=MTIyNjkyMTIzMTE1MzU1OTEzNA%3D%3D.2"
      },
      {
        "code": "8UFPpvFeVE",
        "date": 1443742878,
        "dimensions": {
          "width": 1080,
          "height": 1080
        },
        "comments": {
          "count": 0
        },
        "caption": "#visaourbanaiz",
        "likes": {
          "count": 8
        },
        "owner": {
          "id": "464136400"
        },
        "thumbnail_src": "https://igcdn-photos-a-a.akamaihd.net/hphotos-ak-xaf1/t51.2885-15/s640x640/sh0.08/e35/10818011_893445740691072_237623381_n.jpg?ig_cache_key=MTA4NjUxNjQ3NTk0MTIxNzYwNA%3D%3D.2",
        "is_video": false,
        "id": "1086516475941217604",
        "display_src": "https://igcdn-photos-a-a.akamaihd.net/hphotos-ak-xaf1/t51.2885-15/e35/10818011_893445740691072_237623381_n.jpg?ig_cache_key=MTA4NjUxNjQ3NTk0MTIxNzYwNA%3D%3D.2"
      },
      {
        "code": "BDMV0eyledu",
        "date": 1458515519,
        "dimensions": {
          "width": 1080,
          "height": 1080
        },
        "comments": {
          "count": 1
        },
        "caption": "#saopaulo",
        "likes": {
          "count": 17
        },
        "owner": {
          "id": "464136400"
        },
        "thumbnail_src": "https://igcdn-photos-g-a.akamaihd.net/hphotos-ak-xft1/t51.2885-15/s640x640/sh0.08/e35/1171613_1556074228054846_306064703_n.jpg?ig_cache_key=MTIxMDQzODM2NTMwNjI4Mzg4Ng%3D%3D.2",
        "is_video": false,
        "id": "1210438365306283886",
        "display_src": "https://igcdn-photos-g-a.akamaihd.net/hphotos-ak-xft1/t51.2885-15/e35/1171613_1556074228054846_306064703_n.jpg?ig_cache_key=MTIxMDQzODM2NTMwNjI4Mzg4Ng%3D%3D.2"
      },
      {
        "code": "ceF62iFeVa",
        "dimensions": {
          "width": 612,
          "height": 612
        },
        "comments": {
          "count": 2
        },
        "date": 1375359300,
        "likes": {
          "count": 3
        },
        "owner": {
          "id": "464136400"
        },
        "thumbnail_src": "https://igcdn-photos-c-a.akamaihd.net/hphotos-ak-xpa1/t51.2885-15/e15/11283426_1069675103059922_1850120818_n.jpg?ig_cache_key=NTEyODczNDQyMDgyOTQwMjUw.2",
        "is_video": false,
        "id": "512873442082940250",
        "display_src": "https://igcdn-photos-c-a.akamaihd.net/hphotos-ak-xpa1/t51.2885-15/e15/11283426_1069675103059922_1850120818_n.jpg?ig_cache_key=NTEyODczNDQyMDgyOTQwMjUw.2"
      },
      {
        "code": "cbV2r6leVf",
        "date": 1375266991,
        "dimensions": {
          "width": 612,
          "height": 612
        },
        "comments": {
          "count": 1
        },
        "caption": "Instituto Tomie Ohtake",
        "likes": {
          "count": 9
        },
        "owner": {
          "id": "464136400"
        },
        "thumbnail_src": "https://igcdn-photos-e-a.akamaihd.net/hphotos-ak-xap1/t51.2885-15/e15/11282305_841962155880996_1521101157_n.jpg?ig_cache_key=NTEyMDk5MDk5NjE4OTYwNzM1.2",
        "is_video": false,
        "id": "512099099618960735",
        "display_src": "https://igcdn-photos-e-a.akamaihd.net/hphotos-ak-xap1/t51.2885-15/e15/11282305_841962155880996_1521101157_n.jpg?ig_cache_key=NTEyMDk5MDk5NjE4OTYwNzM1.2"
      },
      {
        "code": "b2SVnlleeL",
        "dimensions": {
          "width": 612,
          "height": 612
        },
        "comments": {
          "count": 3
        },
        "date": 1374023633,
        "likes": {
          "count": 14
        },
        "owner": {
          "id": "464136400"
        },
        "thumbnail_src": "https://igcdn-photos-c-a.akamaihd.net/hphotos-ak-xpa1/t51.2885-15/e15/11352950_448729295304042_2108978973_n.jpg?ig_cache_key=NTAxNjY5MDU4OTUxMTEyNTg3.2",
        "is_video": false,
        "id": "501669058951112587",
        "display_src": "https://igcdn-photos-c-a.akamaihd.net/hphotos-ak-xpa1/t51.2885-15/e15/11352950_448729295304042_2108978973_n.jpg?ig_cache_key=NTAxNjY5MDU4OTUxMTEyNTg3.2"
      },
      {
        "code": "cFXex1lebG",
        "dimensions": {
          "width": 612,
          "height": 612
        },
        "comments": {
          "count": 3
        },
        "date": 1374529646,
        "likes": {
          "count": 18
        },
        "owner": {
          "id": "464136400"
        },
        "thumbnail_src": "https://igcdn-photos-g-a.akamaihd.net/hphotos-ak-xtf1/t51.2885-15/e15/11379815_111835652483478_260435801_n.jpg?ig_cache_key=NTA1OTEzODAzMzE1NDcyMDcw.2",
        "is_video": false,
        "id": "505913803315472070",
        "display_src": "https://igcdn-photos-g-a.akamaihd.net/hphotos-ak-xtf1/t51.2885-15/e15/11379815_111835652483478_260435801_n.jpg?ig_cache_key=NTA1OTEzODAzMzE1NDcyMDcw.2"
      },
      {
        "code": "cFSpCzleTC",
        "date": 1374527109,
        "dimensions": {
          "width": 612,
          "height": 612
        },
        "comments": {
          "count": 2
        },
        "caption": "Casa das Rosas.",
        "likes": {
          "count": 3
        },
        "owner": {
          "id": "464136400"
        },
        "thumbnail_src": "https://igcdn-photos-e-a.akamaihd.net/hphotos-ak-xfa1/t51.2885-15/e15/11377461_434757960037404_1109425246_n.jpg?ig_cache_key=NTA1ODkyNTE4NDk3NzM5OTcw.2",
        "is_video": false,
        "id": "505892518497739970",
        "display_src": "https://igcdn-photos-e-a.akamaihd.net/hphotos-ak-xfa1/t51.2885-15/e15/11377461_434757960037404_1109425246_n.jpg?ig_cache_key=NTA1ODkyNTE4NDk3NzM5OTcw.2"
      },
      {
        "code": "daSLhpFeV8",
        "date": 1377378994,
        "dimensions": {
          "width": 612,
          "height": 612
        },
        "comments": {
          "count": 1
        },
        "caption": "Sesc Pompeia",
        "likes": {
          "count": 12
        },
        "owner": {
          "id": "464136400"
        },
        "thumbnail_src": "https://igcdn-photos-e-a.akamaihd.net/hphotos-ak-xtf1/t51.2885-15/e15/11262761_1450297838618724_376169424_n.jpg?ig_cache_key=NTI5ODE1ODYzMDQzNjc5NjEy.2",
        "is_video": false,
        "id": "529815863043679612",
        "display_src": "https://igcdn-photos-e-a.akamaihd.net/hphotos-ak-xtf1/t51.2885-15/e15/11262761_1450297838618724_376169424_n.jpg?ig_cache_key=NTI5ODE1ODYzMDQzNjc5NjEy.2"
      },
      {
        "code": "eA9YjRFed4",
        "dimensions": {
          "width": 612,
          "height": 612
        },
        "comments": {
          "count": 3
        },
        "date": 1378676713,
        "likes": {
          "count": 6
        },
        "owner": {
          "id": "464136400"
        },
        "thumbnail_src": "https://igcdn-photos-c-a.akamaihd.net/hphotos-ak-xap1/t51.2885-15/e15/11287519_789147667866418_956759214_n.jpg?ig_cache_key=NTQwNzAxOTIzMjU2NjkwNTUy.2",
        "is_video": false,
        "id": "540701923256690552",
        "display_src": "https://igcdn-photos-c-a.akamaihd.net/hphotos-ak-xap1/t51.2885-15/e15/11287519_789147667866418_956759214_n.jpg?ig_cache_key=NTQwNzAxOTIzMjU2NjkwNTUy.2"
      },
      {
        "code": "BDRy1-FlddN",
        "date": 1458698507,
        "dimensions": {
          "width": 640,
          "height": 640
        },
        "comments": {
          "count": 0
        },
        "caption": "#visaourbanaiz",
        "likes": {
          "count": 4
        },
        "owner": {
          "id": "3059271396"
        },
        "thumbnail_src": "https://igcdn-photos-c-a.akamaihd.net/hphotos-ak-xaf1/t51.2885-15/e15/1169749_1731587303753754_1292615217_n.jpg?ig_cache_key=MTIxMTk3MzM4NTg2Mjg5NTQzNw%3D%3D.2",
        "is_video": true,
        "id": "1211973385862895437",
        "display_src": "https://igcdn-photos-c-a.akamaihd.net/hphotos-ak-xaf1/t51.2885-15/e15/1169749_1731587303753754_1292615217_n.jpg?ig_cache_key=MTIxMTk3MzM4NTg2Mjg5NTQzNw%3D%3D.2"
      },
      {
        "code": "BEMfCu9ldck",
        "date": 1460667838,
        "dimensions": {
          "width": 1080,
          "height": 1080
        },
        "comments": {
          "count": 0
        },
        "caption": "#naturezaemsaopaulo #calçadasdavila #streetvila #stretart #vilamadalena #saopaulocity #sãopaulo #sãopaulo #visaourbanaiz",
        "likes": {
          "count": 9
        },
        "owner": {
          "id": "3059271396"
        },
        "thumbnail_src": "https://igcdn-photos-b-a.akamaihd.net/hphotos-ak-xaf1/t51.2885-15/s640x640/sh0.08/e35/12912514_1561894847436161_421864525_n.jpg?ig_cache_key=MTIyODQ5MzMyNTY3MTQ1NDUwMA%3D%3D.2",
        "is_video": false,
        "id": "1228493325671454500",
        "display_src": "https://igcdn-photos-b-a.akamaihd.net/hphotos-ak-xaf1/t51.2885-15/e35/12912514_1561894847436161_421864525_n.jpg?ig_cache_key=MTIyODQ5MzMyNTY3MTQ1NDUwMA%3D%3D.2"
      },
      {
        "code": "BEJUqzkFdWL",
        "date": 1460561736,
        "dimensions": {
          "width": 1080,
          "height": 1080
        },
        "comments": {
          "count": 0
        },
        "caption": "#naturezaemsaopaulo #visaourbanaiz #vilamadalena #topplacesaopaulo #igerssãopaulo #topplacesaopaulo #sãopaulo #ilovesp #sp4you #euamosp #saopaulowalk #SaoPaulo_Originals #instasp #serpaulistano #paulista #soumaissaopaulo #foodsp #foodhunter #sampa #sampafood #saopaulo360 #grafite #stretart #streetvila #sãopaulo #pulsasp",
        "likes": {
          "count": 6
        },
        "owner": {
          "id": "3059271396"
        },
        "thumbnail_src": "https://igcdn-photos-d-a.akamaihd.net/hphotos-ak-xaf1/t51.2885-15/s640x640/sh0.08/e35/12724644_1708167379395587_2012419602_n.jpg?ig_cache_key=MTIyNzYwMzI3NTk0OTY1OTUzMQ%3D%3D.2",
        "is_video": false,
        "id": "1227603275949659531",
        "display_src": "https://igcdn-photos-d-a.akamaihd.net/hphotos-ak-xaf1/t51.2885-15/e35/12724644_1708167379395587_2012419602_n.jpg?ig_cache_key=MTIyNzYwMzI3NTk0OTY1OTUzMQ%3D%3D.2"
      },
      {
        "code": "6XpSJXledw",
        "date": 1439567469,
        "dimensions": {
          "width": 1080,
          "height": 1080
        },
        "comments": {
          "count": 6
        },
        "caption": "Luz",
        "likes": {
          "count": 20
        },
        "owner": {
          "id": "464136400"
        },
        "thumbnail_src": "https://igcdn-photos-a-a.akamaihd.net/hphotos-ak-xft1/t51.2885-15/s640x640/sh0.08/e35/11849054_692433907553448_734001285_n.jpg?ig_cache_key=MTA1MTQ5MDYwNDkzMTIxMzE2OA%3D%3D.2",
        "is_video": false,
        "id": "1051490604931213168",
        "display_src": "https://igcdn-photos-a-a.akamaihd.net/hphotos-ak-xft1/t51.2885-15/e35/11849054_692433907553448_734001285_n.jpg?ig_cache_key=MTA1MTQ5MDYwNDkzMTIxMzE2OA%3D%3D.2"
      },
      {
        "code": "BB0S0WcleXK",
        "date": 1455561155,
        "dimensions": {
          "width": 1080,
          "height": 723
        },
        "comments": {
          "count": 0
        },
        "caption": "#visaourbanaiz",
        "likes": {
          "count": 6
        },
        "owner": {
          "id": "464136400"
        },
        "thumbnail_src": "https://igcdn-photos-d-a.akamaihd.net/hphotos-ak-xpt1/t51.2885-15/s640x640/sh0.08/e35/c178.0.723.723/12479159_956946897715467_1452155349_n.jpg?ig_cache_key=MTE4NTY1NTM2NDI1NzE3OTA4Mg%3D%3D.2.c",
        "is_video": false,
        "id": "1185655364257179082",
        "display_src": "https://igcdn-photos-d-a.akamaihd.net/hphotos-ak-xpt1/t51.2885-15/e35/12479159_956946897715467_1452155349_n.jpg?ig_cache_key=MTE4NTY1NTM2NDI1NzE3OTA4Mg%3D%3D.2"
      },
      {
        "code": "BB0TJPxFeX0",
        "date": 1455561326,
        "dimensions": {
          "width": 1080,
          "height": 723
        },
        "comments": {
          "count": 2
        },
        "caption": "#spglow",
        "likes": {
          "count": 14
        },
        "owner": {
          "id": "464136400"
        },
        "thumbnail_src": "https://igcdn-photos-g-a.akamaihd.net/hphotos-ak-xaf1/t51.2885-15/s640x640/sh0.08/e35/c178.0.723.723/12677343_1121730377860598_642484103_n.jpg?ig_cache_key=MTE4NTY1NjgwMDE5MzkzMDc0MA%3D%3D.2.c",
        "is_video": false,
        "id": "1185656800193930740",
        "display_src": "https://igcdn-photos-g-a.akamaihd.net/hphotos-ak-xaf1/t51.2885-15/e35/12677343_1121730377860598_642484103_n.jpg?ig_cache_key=MTE4NTY1NjgwMDE5MzkzMDc0MA%3D%3D.2"
      },
      {
        "code": "BEPEoRbQbHt",
        "date": 1460754653,
        "dimensions": {
          "width": 1080,
          "height": 720
        },
        "comments": {
          "count": 1
        },
        "caption": "Fotos noturnas luz na escuridão.\n#visaourbanaiz #estudiomadalena #ideazarvos #saopaulo #luz  #noite #silencio #streetphotography #vida @spdagaroa @olharesdesampa",
        "likes": {
          "count": 59
        },
        "owner": {
          "id": "2880834203"
        },
        "thumbnail_src": "https://igcdn-photos-b-a.akamaihd.net/hphotos-ak-xaf1/t51.2885-15/s640x640/sh0.08/e35/c180.0.720.720/12965247_1337892809558009_1679529422_n.jpg?ig_cache_key=MTIyOTIyMTU4Mjk3MTQ0OTgzNw%3D%3D.2.c",
        "is_video": false,
        "id": "1229221582971449837",
        "display_src": "https://igcdn-photos-b-a.akamaihd.net/hphotos-ak-xaf1/t51.2885-15/e35/12965247_1337892809558009_1679529422_n.jpg?ig_cache_key=MTIyOTIyMTU4Mjk3MTQ0OTgzNw%3D%3D.2"
      },
      {
        "code": "BEPDwb8D9pg",
        "date": 1460754195,
        "dimensions": {
          "width": 1080,
          "height": 1080
        },
        "comments": {
          "count": 1
        },
        "caption": "#visaourbanaiz",
        "likes": {
          "count": 99
        },
        "owner": {
          "id": "1570796013"
        },
        "thumbnail_src": "https://igcdn-photos-d-a.akamaihd.net/hphotos-ak-xfa1/t51.2885-15/s640x640/sh0.08/e35/12976130_228143870876867_1940786129_n.jpg?ig_cache_key=MTIyOTIxNzc0NTk2ODU1MjU0NA%3D%3D.2",
        "is_video": false,
        "id": "1229217745968552544",
        "display_src": "https://igcdn-photos-d-a.akamaihd.net/hphotos-ak-xfa1/t51.2885-15/e35/12976130_228143870876867_1940786129_n.jpg?ig_cache_key=MTIyOTIxNzc0NTk2ODU1MjU0NA%3D%3D.2"
      },
      {
        "code": "BEPDu4kIHlb",
        "date": 1460754183,
        "dimensions": {
          "width": 1080,
          "height": 752
        },
        "comments": {
          "count": 0
        },
        "caption": "#visaourbanaiz",
        "likes": {
          "count": 31
        },
        "owner": {
          "id": "4327077"
        },
        "thumbnail_src": "https://igcdn-photos-c-a.akamaihd.net/hphotos-ak-xaf1/t51.2885-15/s640x640/sh0.08/e35/c164.0.752.752/12940086_1570485336577498_1451894008_n.jpg?ig_cache_key=MTIyOTIxNzYzOTI2NjU0ODA1OQ%3D%3D.2.c",
        "is_video": false,
        "id": "1229217639266548059",
        "display_src": "https://igcdn-photos-c-a.akamaihd.net/hphotos-ak-xaf1/t51.2885-15/e35/12940086_1570485336577498_1451894008_n.jpg?ig_cache_key=MTIyOTIxNzYzOTI2NjU0ODA1OQ%3D%3D.2"
      },
      {
        "code": "BEPDCThoHkB",
        "date": 1460753817,
        "dimensions": {
          "width": 1080,
          "height": 718
        },
        "comments": {
          "count": 0
        },
        "caption": "#visaourbanaiz",
        "likes": {
          "count": 42
        },
        "owner": {
          "id": "4327077"
        },
        "thumbnail_src": "https://igcdn-photos-h-a.akamaihd.net/hphotos-ak-xfa1/t51.2885-15/s640x640/sh0.08/e35/c181.0.718.718/12976688_570317819799287_796360557_n.jpg?ig_cache_key=MTIyOTIxNDU3NTgzOTE4MTA1Nw%3D%3D.2.c",
        "is_video": false,
        "id": "1229214575839181057",
        "display_src": "https://igcdn-photos-h-a.akamaihd.net/hphotos-ak-xfa1/t51.2885-15/e35/12976688_570317819799287_796360557_n.jpg?ig_cache_key=MTIyOTIxNDU3NTgzOTE4MTA1Nw%3D%3D.2"
      },
      {
        "code": "BEPA8UXFeSP",
        "date": 1460752720,
        "dimensions": {
          "width": 1080,
          "height": 723
        },
        "comments": {
          "count": 0
        },
        "caption": "Copan #visaourbanaiz",
        "likes": {
          "count": 13
        },
        "owner": {
          "id": "464136400"
        },
        "thumbnail_src": "https://igcdn-photos-g-a.akamaihd.net/hphotos-ak-xaf1/t51.2885-15/s640x640/sh0.08/e35/c178.0.723.723/12965044_1015398308535550_671173486_n.jpg?ig_cache_key=MTIyOTIwNTM2ODMyNjE4NjEyNw%3D%3D.2.c",
        "is_video": false,
        "id": "1229205368326186127",
        "display_src": "https://igcdn-photos-g-a.akamaihd.net/hphotos-ak-xaf1/t51.2885-15/e35/12965044_1015398308535550_671173486_n.jpg?ig_cache_key=MTIyOTIwNTM2ODMyNjE4NjEyNw%3D%3D.2"
      },
      {
        "code": "BEO_inqoHss",
        "date": 1460751985,
        "dimensions": {
          "width": 1080,
          "height": 886
        },
        "comments": {
          "count": 0
        },
        "caption": "#visaourbanaiz",
        "likes": {
          "count": 40
        },
        "owner": {
          "id": "4327077"
        },
        "thumbnail_src": "https://igcdn-photos-e-a.akamaihd.net/hphotos-ak-xfa1/t51.2885-15/s640x640/sh0.08/e35/c97.0.886.886/12917796_221848364846444_623844321_n.jpg?ig_cache_key=MTIyOTE5OTIwNDMwMjIyNDE3Mg%3D%3D.2.c",
        "is_video": false,
        "id": "1229199204302224172",
        "display_src": "https://igcdn-photos-e-a.akamaihd.net/hphotos-ak-xfa1/t51.2885-15/e35/12917796_221848364846444_623844321_n.jpg?ig_cache_key=MTIyOTE5OTIwNDMwMjIyNDE3Mg%3D%3D.2"
      },
      {
        "code": "BEO_b0ZIHsf",
        "date": 1460751929,
        "dimensions": {
          "width": 1080,
          "height": 718
        },
        "comments": {
          "count": 0
        },
        "caption": "#visaourbanaiz",
        "likes": {
          "count": 37
        },
        "owner": {
          "id": "4327077"
        },
        "thumbnail_src": "https://igcdn-photos-a-a.akamaihd.net/hphotos-ak-xaf1/t51.2885-15/s640x640/sh0.08/e35/c181.0.718.718/12918596_556805651163872_1488576596_n.jpg?ig_cache_key=MTIyOTE5ODczNjkzMDkyOTQzOQ%3D%3D.2.c",
        "is_video": false,
        "id": "1229198736930929439",
        "display_src": "https://igcdn-photos-a-a.akamaihd.net/hphotos-ak-xaf1/t51.2885-15/e35/12918596_556805651163872_1488576596_n.jpg?ig_cache_key=MTIyOTE5ODczNjkzMDkyOTQzOQ%3D%3D.2"
      },
      {
        "code": "BCBWFEUFeSd",
        "date": 1455999072,
        "dimensions": {
          "width": 1080,
          "height": 1080
        },
        "comments": {
          "count": 2
        },
        "caption": "Prédio lindo",
        "likes": {
          "count": 10
        },
        "owner": {
          "id": "464136400"
        },
        "thumbnail_src": "https://igcdn-photos-e-a.akamaihd.net/hphotos-ak-xtf1/t51.2885-15/s640x640/sh0.08/e35/11377764_1532735177025852_605403391_n.jpg?ig_cache_key=MTE4OTMyODg4MTg1NTA5NTk2NQ%3D%3D.2",
        "is_video": false,
        "id": "1189328881855095965",
        "display_src": "https://igcdn-photos-e-a.akamaihd.net/hphotos-ak-xtf1/t51.2885-15/e35/11377764_1532735177025852_605403391_n.jpg?ig_cache_key=MTE4OTMyODg4MTg1NTA5NTk2NQ%3D%3D.2"
      },
      {
        "code": "BEO99_AIHpq",
        "date": 1460751161,
        "dimensions": {
          "width": 1080,
          "height": 719
        },
        "comments": {
          "count": 0
        },
        "caption": "as manifestações de 2013 #visaourbanaiz",
        "likes": {
          "count": 34
        },
        "owner": {
          "id": "4327077"
        },
        "thumbnail_src": "https://igcdn-photos-a-a.akamaihd.net/hphotos-ak-xaf1/t51.2885-15/s640x640/sh0.08/e35/c180.0.719.719/12965048_987617688034560_8235614_n.jpg?ig_cache_key=MTIyOTE5MjI4ODY5MTg0NTczOA%3D%3D.2.c",
        "is_video": false,
        "id": "1229192288691845738",
        "display_src": "https://igcdn-photos-a-a.akamaihd.net/hphotos-ak-xaf1/t51.2885-15/e35/12965048_987617688034560_8235614_n.jpg?ig_cache_key=MTIyOTE5MjI4ODY5MTg0NTczOA%3D%3D.2"
      },
      {
        "code": "5hLtjjSJXv",
        "date": 1437740026,
        "dimensions": {
          "width": 1080,
          "height": 1080
        },
        "comments": {
          "count": 0
        },
        "caption": "#streetPhotography #square #pinheiros #iphoneShots #pb #saopaulo #visaourbanaiz",
        "likes": {
          "count": 0
        },
        "owner": {
          "id": "15169644"
        },
        "thumbnail_src": "https://igcdn-photos-d-a.akamaihd.net/hphotos-ak-xft1/t51.2885-15/s640x640/sh0.08/e35/11356001_872671449483483_2016925340_n.jpg?ig_cache_key=MTAzNjE2MDg5ODMzMjkyMzM3NQ%3D%3D.2",
        "is_video": false,
        "id": "1036160898332923375",
        "display_src": "https://igcdn-photos-d-a.akamaihd.net/hphotos-ak-xft1/t51.2885-15/e35/11356001_872671449483483_2016925340_n.jpg?ig_cache_key=MTAzNjE2MDg5ODMzMjkyMzM3NQ%3D%3D.2"
      },
      {
        "code": "9BtpXlSJdf",
        "date": 1445274010,
        "dimensions": {
          "width": 1080,
          "height": 1080
        },
        "comments": {
          "count": 0
        },
        "caption": "Adoro esse lugar. #becodoBatman 🇺🇸 love this place #vilamadalena #goprophotography #gopro #hero3+ #vivaspcity #olharesdesampa #visaourbanaiz",
        "likes": {
          "count": 17
        },
        "owner": {
          "id": "15169644"
        },
        "thumbnail_src": "https://igcdn-photos-f-a.akamaihd.net/hphotos-ak-xpt1/t51.2885-15/s640x640/sh0.08/e35/12106182_972183122841069_22575215_n.jpg?ig_cache_key=MTA5OTM2MDUzODk2ODIzMzgyMw%3D%3D.2",
        "is_video": false,
        "id": "1099360538968233823",
        "display_src": "https://igcdn-photos-f-a.akamaihd.net/hphotos-ak-xpt1/t51.2885-15/e35/12106182_972183122841069_22575215_n.jpg?ig_cache_key=MTA5OTM2MDUzODk2ODIzMzgyMw%3D%3D.2"
      },
      {
        "code": "BA4ioIBSJeq",
        "date": 1453556177,
        "dimensions": {
          "width": 1080,
          "height": 1080
        },
        "comments": {
          "count": 0
        },
        "caption": "#vejasp #splovers #lovesp #streetphotography #vivaspcity #cidadedagaroa #visaourbanaiz",
        "likes": {
          "count": 8
        },
        "owner": {
          "id": "15169644"
        },
        "thumbnail_src": "https://igcdn-photos-b-a.akamaihd.net/hphotos-ak-xta1/t51.2885-15/s640x640/sh0.08/e35/12479211_529915693845121_1577075417_n.jpg?ig_cache_key=MTE2ODgzNjM5NDI3NDU1OTkxNA%3D%3D.2",
        "is_video": false,
        "id": "1168836394274559914",
        "display_src": "https://igcdn-photos-b-a.akamaihd.net/hphotos-ak-xta1/t51.2885-15/e35/12479211_529915693845121_1577075417_n.jpg?ig_cache_key=MTE2ODgzNjM5NDI3NDU1OTkxNA%3D%3D.2"
      },
      {
        "code": "BBkOOy5SJZc",
        "date": 1455021879,
        "dimensions": {
          "width": 1080,
          "height": 810
        },
        "comments": {
          "count": 2
        },
        "caption": "#olharesdesampa #sp4you #spcity #splovers #nasruasdesp011 #streetphotography #vivasp #church #igrejas #vejasp #visaourbanaiz",
        "likes": {
          "count": 10
        },
        "owner": {
          "id": "15169644"
        },
        "thumbnail_src": "https://igcdn-photos-g-a.akamaihd.net/hphotos-ak-xta1/t51.2885-15/s640x640/sh0.08/e35/c135.0.810.810/12568707_541610279341734_1606831824_n.jpg?ig_cache_key=MTE4MTEzMTU5MTY0OTg5MTkzMg%3D%3D.2.c",
        "is_video": false,
        "id": "1181131591649891932",
        "display_src": "https://igcdn-photos-g-a.akamaihd.net/hphotos-ak-xta1/t51.2885-15/e35/12568707_541610279341734_1606831824_n.jpg?ig_cache_key=MTE4MTEzMTU5MTY0OTg5MTkzMg%3D%3D.2"
      },
      {
        "code": "BBdqe0_yJYM",
        "date": 1454801809,
        "dimensions": {
          "width": 1080,
          "height": 1080
        },
        "comments": {
          "count": 1
        },
        "caption": "Casinha em uma travessa da av #pompeia. 🇺🇸old house in the neighborhood of Pompeia - Sao Paulo - Brazil #olharesdesampa #splovers #spcity #vivasp #nasruasdesp011 #sp4you @saopauloantiga #streetphotography #architeture #saopaulodagaroa #visaourbanaiz",
        "likes": {
          "count": 22
        },
        "owner": {
          "id": "15169644"
        },
        "thumbnail_src": "https://igcdn-photos-e-a.akamaihd.net/hphotos-ak-xap1/t51.2885-15/s640x640/sh0.08/e35/12547566_543814432462396_698914524_n.jpg?ig_cache_key=MTE3OTI4NTUxMzg4MzM5MTUwMA%3D%3D.2",
        "is_video": false,
        "id": "1179285513883391500",
        "display_src": "https://igcdn-photos-e-a.akamaihd.net/hphotos-ak-xap1/t51.2885-15/e35/12547566_543814432462396_698914524_n.jpg?ig_cache_key=MTE3OTI4NTUxMzg4MzM5MTUwMA%3D%3D.2"
      },
      {
        "code": "BEBoxmcyJWi",
        "date": 1460303841,
        "dimensions": {
          "width": 1080,
          "height": 1080
        },
        "comments": {
          "count": 0
        },
        "caption": "Resistindo ao tempo! #streetphotography #iphoneshots #vintage  #architecture #vilamadalena #visaourbanaiz #minhasaopaulo #nasruasdesp011",
        "likes": {
          "count": 12
        },
        "owner": {
          "id": "15169644"
        },
        "thumbnail_src": "https://igcdn-photos-c-a.akamaihd.net/hphotos-ak-xaf1/t51.2885-15/s640x640/sh0.08/e35/12912854_1696888330558290_1983127245_n.jpg?ig_cache_key=MTIyNTQzOTkwNDAyMTM4NjY1OA%3D%3D.2",
        "is_video": false,
        "id": "1225439904021386658",
        "display_src": "https://igcdn-photos-c-a.akamaihd.net/hphotos-ak-xaf1/t51.2885-15/e35/12912854_1696888330558290_1983127245_n.jpg?ig_cache_key=MTIyNTQzOTkwNDAyMTM4NjY1OA%3D%3D.2"
      }
    ]
  }
}
